odoo/addons/product_operating_unit/README.rst
odoo/addons/product_operating_unit/__init__.py
odoo/addons/product_operating_unit/__manifest__.py
odoo/addons/product_operating_unit/i18n/es.po
odoo/addons/product_operating_unit/i18n/it.po
odoo/addons/product_operating_unit/i18n/ja.po
odoo/addons/product_operating_unit/i18n/product_operating_unit.pot
odoo/addons/product_operating_unit/i18n/pt.po
odoo/addons/product_operating_unit/models/__init__.py
odoo/addons/product_operating_unit/models/product_category.py
odoo/addons/product_operating_unit/models/product_template.py
odoo/addons/product_operating_unit/readme/CONTRIBUTORS.md
odoo/addons/product_operating_unit/readme/DESCRIPTION.md
odoo/addons/product_operating_unit/readme/ROADMAP.md
odoo/addons/product_operating_unit/readme/USAGE.md
odoo/addons/product_operating_unit/security/product_template_security.xml
odoo/addons/product_operating_unit/static/description/icon.png
odoo/addons/product_operating_unit/static/description/index.html
odoo/addons/product_operating_unit/tests/__init__.py
odoo/addons/product_operating_unit/tests/test_product_operating_unit.py
odoo/addons/product_operating_unit/views/product_category_view.xml
odoo/addons/product_operating_unit/views/product_template_view.xml
odoo_addon_product_operating_unit-17.0.1.0.0.3.dist-info/METADATA
odoo_addon_product_operating_unit-17.0.1.0.0.3.dist-info/WHEEL
odoo_addon_product_operating_unit-17.0.1.0.0.3.dist-info/top_level.txt
odoo_addon_product_operating_unit-17.0.1.0.0.3.dist-info/RECORD
